ja_timex/__init__.py
ja_timex/dictionary/filter_unit.json
ja_timex/dictionary/partial_phrase_affix.json
ja_timex/dictionary/wareki.json
ja_timex/extract_filter.py
ja_timex/number_normalizer.py
ja_timex/pattern/abstime.py
ja_timex/pattern/duration.py
ja_timex/pattern/place.py
ja_timex/pattern/reltime.py
ja_timex/pattern/set.py
ja_timex/tag.py
ja_timex/tagger.py
ja_timex/timex.py
ja_timex/util.py
ja_timex-0.2.7.dist-info/LICENSE
ja_timex-0.2.7.dist-info/WHEEL
ja_timex-0.2.7.dist-info/METADATA
ja_timex-0.2.7.dist-info/RECORD
