Metadata-Version: 2.1
Name: ja-timex
Version: 0.2.7
Summary: Analyze and parse natural language temporal expression from Japanese sentences
Home-page: https://github.com/yagays/ja-timex
License: MIT
Keywords: ja_timex,NLP,japanese
Author: Yuki Okuda
Author-email: y.okuda@dr-ubie.com
Requires-Python: >=3.7.1,<4.0.0
Classifier: Development Status :: 4 - Beta
Classifier: License :: OSI Approved :: MIT License
Classifier: Natural Language :: Japanese
Classifier: Programming Language :: Python :: 3
Classifier: Programming Language :: Python :: 3.8
Classifier: Programming Language :: Python :: 3.9
Classifier: Programming Language :: Python :: 3.10
Classifier: Programming Language :: Python :: 3
Classifier: Programming Language :: Python :: 3.7
Classifier: Programming Language :: Python :: 3.8
Classifier: Programming Language :: Python :: 3.9
Classifier: Topic :: Software Development :: Libraries :: Python Modules
Classifier: Topic :: Text Processing :: Linguistic
Requires-Dist: mojimoji (>=0.0.11,<0.0.12)
Requires-Dist: pendulum (>=2.1.2,<3.0.0)
Project-URL: Repository, https://github.com/yagays/ja-timex
